[{"name": "paddings", "ph": "B", "pid": "1", "ts": "77483"}, {"name": "paddings", "ph": "E", "pid": "1", "ts": "77487"}, {"name": "stack", "ph": "B", "pid": "1", "ts": "77495"}, {"name": "stack", "ph": "E", "pid": "1", "ts": "77497"}, {"name": "stack_1", "ph": "B", "pid": "1", "ts": "77503"}, {"name": "stack_1", "ph": "E", "pid": "1", "ts": "77506"}, {"name": "stack_2", "ph": "B", "pid": "1", "ts": "77512"}, {"name": "stack_2", "ph": "E", "pid": "1", "ts": "77515"}, {"name": "Relu", "ph": "B", "pid": "1", "ts": "77521"}, {"name": "Relu", "ph": "E", "pid": "1", "ts": "78550"}, {"name": "Relu_1", "ph": "B", "pid": "2", "ts": "77571"}, {"name": "Relu_1", "ph": "E", "pid": "2", "ts": "78584"}, {"name": "Conv2D", "ph": "B", "pid": "2", "ts": "78599"}, {"name": "Conv2D", "ph": "E", "pid": "2", "ts": "78643"}, {"name": "split", "ph": "B", "pid": "2", "ts": "78651"}, {"name": "split", "ph": "E", "pid": "2", "ts": "78684"}, {"name": "Relu", "ph": "B", "pid": "2", "ts": "78691"}, {"name": "Relu", "ph": "E", "pid": "2", "ts": "78715"}, {"name": "MaxPool", "ph": "B", "pid": "2", "ts": "78723"}, {"name": "MaxPool", "ph": "E", "pid": "2", "ts": "78761"}, {"name": "Relu", "ph": "B", "pid": "2", "ts": "78768"}, {"name": "Relu", "ph": "E", "pid": "2", "ts": "78792"}, {"name": "Relu", "ph": "B", "pid": "2", "ts": "78799"}, {"name": "Relu", "ph": "E", "pid": "2", "ts": "78822"}, {"name": "MaxPool", "ph": "B", "pid": "2", "ts": "78829"}, {"name": "MaxPool", "ph": "E", "pid": "2", "ts": "78856"}, {"name": "AvgPool", "ph": "B", "pid": "1", "ts": "78561"}, {"name": "AvgPool", "ph": "E", "pid": "1", "ts": "79263"}, {"name": "Pad_Gather_Index", "ph": "B", "pid": "1", "ts": "79273"}, {"name": "Pad_Gather_Index", "ph": "E", "pid": "1", "ts": "79276"}, {"name": "Pad_Gather", "ph": "B", "pid": "1", "ts": "79284"}, {"name": "Pad_Gather", "ph": "E", "pid": "1", "ts": "79287"}, {"name": "Pad", "ph": "B", "pid": "1", "ts": "79292"}, {"name": "Pad", "ph": "E", "pid": "1", "ts": "80562"}, {"name": "Conv2D", "ph": "B", "pid": "1", "ts": "80577"}, {"name": "Conv2D", "ph": "E", "pid": "1", "ts": "81508"}, {"name": "strided_slice", "ph": "B", "pid": "1", "ts": "81522"}, {"name": "strided_slice", "ph": "E", "pid": "1", "ts": "85560"}, {"name": "depthwise", "ph": "B", "pid": "2", "ts": "78890"}, {"name": "depthwise", "ph": "E", "pid": "2", "ts": "86991"}, {"name": "strided_slice", "ph": "B", "pid": "1", "ts": "85577"}, {"name": "strided_slice", "ph": "E", "pid": "1", "ts": "87023"}, {"name": "depthwise", "ph": "B", "pid": "2", "ts": "87002"}, {"name": "depthwise", "ph": "E", "pid": "2", "ts": "87961"}, {"name": "AvgPool_1", "ph": "B", "pid": "1", "ts": "87040"}, {"name": "AvgPool_1", "ph": "E", "pid": "1", "ts": "88622"}, {"name": "depthwise", "ph": "B", "pid": "2", "ts": "87970"}, {"name": "depthwise", "ph": "E", "pid": "2", "ts": "88743"}, {"name": "separable_conv2d", "ph": "B", "pid": "2", "ts": "88753"}, {"name": "separable_conv2d", "ph": "E", "pid": "2", "ts": "88810"}, {"name": "separable_conv2d", "ph": "B", "pid": "2", "ts": "88818"}, {"name": "separable_conv2d", "ph": "E", "pid": "2", "ts": "88852"}, {"name": "separable_conv2d", "ph": "B", "pid": "2", "ts": "88860"}, {"name": "separable_conv2d", "ph": "E", "pid": "2", "ts": "88897"}, {"name": "AvgPool_1", "ph": "B", "pid": "1", "ts": "88643"}, {"name": "AvgPool_1", "ph": "E", "pid": "1", "ts": "89370"}, {"name": "depthwise", "ph": "B", "pid": "2", "ts": "88906"}, {"name": "depthwise", "ph": "E", "pid": "2", "ts": "90137"}, {"name": "Conv2D", "ph": "B", "pid": "1", "ts": "89381"}, {"name": "Conv2D", "ph": "E", "pid": "1", "ts": "90200"}, {"name": "concat", "ph": "B", "pid": "1", "ts": "90213"}, {"name": "concat", "ph": "E", "pid": "1", "ts": "90639"}, {"name": "FusedBatchNorm", "ph": "B", "pid": "1", "ts": "90649"}, {"name": "FusedBatchNorm", "ph": "E", "pid": "1", "ts": "90846"}, {"name": "depthwise", "ph": "B", "pid": "2", "ts": "90147"}, {"name": "depthwise", "ph": "E", "pid": "2", "ts": "90917"}, {"name": "Relu", "ph": "B", "pid": "1", "ts": "90856"}, {"name": "Relu", "ph": "E", "pid": "1", "ts": "91113"}, {"name": "MaxPool", "ph": "B", "pid": "1", "ts": "91135"}, {"name": "MaxPool", "ph": "E", "pid": "1", "ts": "91493"}, {"name": "Relu", "ph": "B", "pid": "1", "ts": "91502"}, {"name": "Relu", "ph": "E", "pid": "1", "ts": "91612"}, {"name": "depthwise", "ph": "B", "pid": "2", "ts": "90927"}, {"name": "depthwise", "ph": "E", "pid": "2", "ts": "92391"}, {"name": "depthwise", "ph": "B", "pid": "1", "ts": "91621"}, {"name": "depthwise", "ph": "E", "pid": "1", "ts": "92397"}, {"name": "separable_conv2d", "ph": "B", "pid": "2", "ts": "92404"}, {"name": "separable_conv2d", "ph": "E", "pid": "2", "ts": "92450"}, {"name": "separable_conv2d", "ph": "B", "pid": "2", "ts": "92458"}, {"name": "separable_conv2d", "ph": "E", "pid": "2", "ts": "92489"}, {"name": "separable_conv2d", "ph": "B", "pid": "2", "ts": "92497"}, {"name": "separable_conv2d", "ph": "E", "pid": "2", "ts": "92535"}, {"name": "add", "ph": "B", "pid": "2", "ts": "92545"}, {"name": "add", "ph": "E", "pid": "2", "ts": "92580"}, {"name": "add", "ph": "B", "pid": "2", "ts": "92590"}, {"name": "add", "ph": "E", "pid": "2", "ts": "92615"}, {"name": "add", "ph": "B", "pid": "2", "ts": "92624"}, {"name": "add", "ph": "E", "pid": "2", "ts": "92661"}, {"name": "add", "ph": "B", "pid": "2", "ts": "92670"}, {"name": "add", "ph": "E", "pid": "2", "ts": "92698"}, {"name": "Relu", "ph": "B", "pid": "2", "ts": "92706"}, {"name": "Relu", "ph": "E", "pid": "2", "ts": "92838"}, {"name": "depthwise", "ph": "B", "pid": "1", "ts": "92413"}, {"name": "depthwise", "ph": "E", "pid": "1", "ts": "92893"}, {"name": "separable_conv2d", "ph": "B", "pid": "1", "ts": "92904"}, {"name": "separable_conv2d", "ph": "E", "pid": "1", "ts": "93141"}, {"name": "separable_conv2d", "ph": "B", "pid": "1", "ts": "93149"}, {"name": "separable_conv2d", "ph": "E", "pid": "1", "ts": "93361"}, {"name": "depthwise", "ph": "B", "pid": "1", "ts": "93369"}, {"name": "depthwise", "ph": "E", "pid": "1", "ts": "93869"}, {"name": "depthwise", "ph": "B", "pid": "2", "ts": "92845"}, {"name": "depthwise", "ph": "E", "pid": "2", "ts": "93987"}, {"name": "depthwise", "ph": "B", "pid": "1", "ts": "93877"}, {"name": "depthwise", "ph": "E", "pid": "1", "ts": "94048"}, {"name": "separable_conv2d", "ph": "B", "pid": "2", "ts": "93998"}, {"name": "separable_conv2d", "ph": "E", "pid": "2", "ts": "94052"}, {"name": "separable_conv2d", "ph": "B", "pid": "1", "ts": "94055"}, {"name": "separable_conv2d", "ph": "E", "pid": "1", "ts": "94252"}, {"name": "separable_conv2d", "ph": "B", "pid": "1", "ts": "94276"}, {"name": "separable_conv2d", "ph": "E", "pid": "1", "ts": "94475"}, {"name": "add", "ph": "B", "pid": "1", "ts": "94484"}, {"name": "add", "ph": "E", "pid": "1", "ts": "94525"}, {"name": "add", "ph": "B", "pid": "1", "ts": "94533"}, {"name": "add", "ph": "E", "pid": "1", "ts": "94725"}, {"name": "add", "ph": "B", "pid": "1", "ts": "94732"}, {"name": "add", "ph": "E", "pid": "1", "ts": "94768"}, {"name": "depthwise", "ph": "B", "pid": "2", "ts": "94061"}, {"name": "depthwise", "ph": "E", "pid": "2", "ts": "94778"}, {"name": "separable_conv2d", "ph": "B", "pid": "2", "ts": "94789"}, {"name": "separable_conv2d", "ph": "E", "pid": "2", "ts": "94839"}, {"name": "add", "ph": "B", "pid": "2", "ts": "94847"}, {"name": "add", "ph": "E", "pid": "2", "ts": "94880"}, {"name": "add", "ph": "B", "pid": "2", "ts": "94889"}, {"name": "add", "ph": "E", "pid": "2", "ts": "94913"}, {"name": "add", "ph": "B", "pid": "2", "ts": "94923"}, {"name": "add", "ph": "E", "pid": "2", "ts": "94955"}, {"name": "concat", "ph": "B", "pid": "2", "ts": "94963"}, {"name": "concat", "ph": "E", "pid": "2", "ts": "95331"}, {"name": "Relu", "ph": "B", "pid": "1", "ts": "94774"}, {"name": "Relu", "ph": "E", "pid": "1", "ts": "96447"}, {"name": "Conv2D", "ph": "B", "pid": "1", "ts": "96463"}, {"name": "Conv2D", "ph": "E", "pid": "1", "ts": "96966"}, {"name": "add", "ph": "B", "pid": "1", "ts": "96981"}, {"name": "add", "ph": "E", "pid": "1", "ts": "97078"}, {"name": "concat", "ph": "B", "pid": "1", "ts": "97098"}, {"name": "concat", "ph": "E", "pid": "1", "ts": "97260"}, {"name": "concat", "ph": "B", "pid": "1", "ts": "97332"}, {"name": "concat", "ph": "E", "pid": "1", "ts": "100270"}]